MANIFEST.in
README.rst
setup.py
docs/images/dummy
docs/images/mktree.0.png
docs/images/rst.0.png
efdir/__init__.py
efdir/bin.py
efdir/csv.py
efdir/etree.py
efdir/fobj.py
efdir/fs.py
efdir/jsoncfg.py
efdir/mktree.py
efdir/primitive.py
efdir/r2x.py
efdir/rstcfg.py
efdir.egg-info/PKG-INFO
efdir.egg-info/SOURCES.txt
efdir.egg-info/dependency_links.txt
efdir.egg-info/entry_points.txt
efdir.egg-info/requires.txt
efdir.egg-info/top_level.txt
efdir/BIN/__init__.py
efdir/BIN/csv2cols.py
efdir/BIN/csv2dtb.py
efdir/BIN/csv2jsd.py
efdir/BIN/repl_suffix.py